{
    "status": "ok",
    "totalResults": 38,
    "articles": [
        {
            "source": {
                "id": null,
                "name": "Hindustan Times"
            },
            "author": "HT News Desk",
            "title": "Congress alleges 'Operation Lotus' as 3 J'khand MLAs caught with cash in Bengal - Hindustan Times",
            "description": "The Congress has been accusing the BJP of trying to topple its coalition government led by Hemant Soren in Jharkhand. | Latest News India",
            "url": "https://www.hindustantimes.com/india-news/operation-lotus-exposed-congress-on-3-jharkhand-mlas-caught-with-cash-101659230815171.html",
            "urlToImage": "https://images.hindustantimes.com/img/2022/07/31/1600x900/congress_bjp_operation_lotus_1659233519029_1659233519197_1659233519197.jpg",
            "publishedAt": "2022-07-31T01:58:38Z",
            "content": "The Congress on Saturday alleged that the BJP's \"Operation Lotus\" in Jharkhand has been exposed after three party MLAs were caught with huge amount of cash in West Bengal's Howrah. The Congress has b… [+1760 chars]"
        },
        {
            "source": {
                "id": null,
                "name": "Business Standard"
            },
            "author": "IANS",
            "title": "Spanish health ministry confirms second death from monkeypox virus - Business Standard",
            "description": "The Spanish Health Ministry has confirmed the countrys second death from the Monkeypox virus",
            "url": "https://www.business-standard.com/article/international/spanish-health-ministry-confirms-second-death-from-monkeypox-virus-122073100023_1.html",
            "urlToImage": "https://bsmedia.business-standard.com/_media/bs/img/article/2022-07/27/full/1658933503-792.jpg",
            "publishedAt": "2022-07-31T01:30:00Z",
            "content": "The Spanish Health Ministry has confirmed the country's second death from the Monkeypox virus.\r\nThe news comes less than 24 hours after the first death from the disease was reported by the Ministry o… [+2487 chars]"
        },
        {
            "source": {
                "id": null,
                "name": "Hindustan Times"
            },
            "author": "HT Tech",
            "title": "Garena Free Fire redeem codes for July 31, 2022: Grab Steamed Bun Grenade, freebies today - HT Tech",
            "description": "Garena Free Fire redeem codes for July 31, 2022: Players can grab the Steamed Bun Grenade and other freebies today. Here is what they need to do.",
            "url": "https://tech.hindustantimes.com/tech/news/garena-free-fire-redeem-codes-for-july-31-2022-grab-steamed-bun-grenade-freebies-today-71659228392538.html",
            "urlToImage": "https://images.hindustantimes.com/tech/img/2022/07/31/1600x900/cae429b44dbf585f8628cfe0ad0d2713jpg_1639967196749_1659228708053_1659228708053.jpg",
            "publishedAt": "2022-07-31T00:52:39Z",
            "content": "Garena Free Fire redeem codes for July 31, 2022: Garena Free Fire players you need to hurry! Today is the last day for you to grab the Steamed Bun Grenade. All you need to do is pre-order the new Kun… [+2019 chars]"
        },
        {
            "source": {
                "id": null,
                "name": "The New Indian Express"
            },
            "author": "Bosky Khanna",
            "title": "Breaking infection chain at early stage crucial to prevent monkeypox spread: Expert - The New Indian Express",
            "description": "After Covid-19, the fear of monkeypox is now on the rise.",
            "url": "https://www.newindianexpress.com/states/karnataka/2022/jul/31/breaking-infection-chain-at-early-stage-crucial-to-prevent-monkeypox-spread-expert-2482488.html",
            "urlToImage": "https://images.newindianexpress.com/uploads/user/imagelibrary/2022/7/29/w600X390/Monkeypox_1_.jpg",
            "publishedAt": "2022-07-31T00:50:00Z",
            "content": "BENGALURU: After Covid-19, the fear of monkeypox is now on the rise. Though this is a self-limiting disease in most people, the symptoms can last from two to four weeks. Dr Giridhar R Babu, Professor… [+10270 chars]"
        },
        {
            "source": {
                "id": null,
                "name": "Livemint"
            },
            "author": "Sounak Mukhopadhyay",
            "title": "Monkeypox in India: Andhra child shows symptoms, gets isolated | Mint - Mint",
            "description": "On July 30, authorities in Guntur, Andhra Pradesh announced that an 8-year-old boy had symptoms of monkeypox.",
            "url": "https://www.livemint.com/news/india/monkeypox-in-india-andhra-child-shows-symptoms-gets-isolated-11659227661655.html",
            "urlToImage": "https://images.livemint.com/img/2022/07/31/600x338/Monkeypox-children_cases_1659110296202_1659228491583_1659228491583.jpg",
            "publishedAt": "2022-07-31T00:48:43Z",
            "content": "An 8-year-old boy in Guntur, Andhra Pradesh reported signs of monkeypox, according to officials. The Government General Hospital in Guntur received the child as an inpatient. Dr. Sumaiya Khan, the Di… [+2343 chars]"
        },
        {
            "source": {
                "id": null,
                "name": "The Indian Express"
            },
            "author": "Mihir Vasavda",
            "title": "Mirabai Chanu wins India's first gold medal at Commonwealth Games, 'can snatch over 90kg' physio claims - The Indian Express",
            "description": "Tokyo Olympics silver medallist defends her CWG title but her main target remains World Championship in December and the Olympic qualification cycle that begins in the same month",
            "url": "https://indianexpress.com/article/sports/commonwealth-games/mirabai-chanu-wins-indias-first-gold-medal-commonwealth-games-can-snatch-over-90kg-physio-claims-8061398/",
            "urlToImage": "https://images.indianexpress.com/2022/07/Chanu.jpg",
            "publishedAt": "2022-07-31T00:42:43Z",
            "content": "Nearly 20 minutes into her warm-up routine, Mirabai Chanu displays otherworldly levels of flexibility not much unlike Neeraj Chopras insane medicine ball stretch, which broke the internet last year.W… [+7056 chars]"
        },
        {
            "source": {
                "id": null,
                "name": "The Tribune India"
            },
            "author": "The Tribune India",
            "title": "Punjab CM Bhagwant Mann apologises to Dr Raj Bahadur for health minister's rude behaviour, requests him to stay on - The Tribune India",
            "description": "Punjab Chief Minister Bhagwant Mann on Saturday apologised to veteran surgeon Dr Raj Bahadur for the humiliation he received at the hands of Health Minister Chetan Singh Jauramajra.",
            "url": "https://www.tribuneindia.com/news/punjab/cm-bhagwant-mann-apologises-to-dr-raj-bahadur-for-health-ministers-rude-behaviour-requests-him-to-stay-417167",
            "urlToImage": "https://englishtribuneimages.blob.core.windows.net/gallary-content/2022/7/2022_7$largeimg_1441774507.jpg",
            "publishedAt": "2022-07-31T00:19:00Z",
            "content": "Tribune News Service\r\nVishav Bharti\r\nChandigarh, July 30\r\nPunjab Chief Minister Bhagwant Mann on Saturday apologised to veteran surgeon Dr Raj Bahadur for the humiliation he received at the hands of … [+1688 chars]"
        },
        {
            "source": {
                "id": null,
                "name": "Hindustan Times"
            },
            "author": "HT News Desk",
            "title": "'Whose Hindi is perhaps like mine': Shashi Tharoor on 'rashtrapatni' row - Hindustan Times",
            "description": "Shashi Tharoor said Adhir Chowdhury was not allowed to speak in the Lok Sabha but when Smriti Irani started speaking – during which she demanded Sonia Gandhi's apology – she was allowed to speak for 10 minutes.  | Latest News India",
            "url": "https://www.hindustantimes.com/india-news/whose-hindi-is-perhaps-like-mine-shashi-tharoor-on-rashtrapatni-row-when-smriti-irani-101659225812540.html",
            "urlToImage": "https://images.hindustantimes.com/img/2022/07/31/1600x900/shashi_1659225822701_1659225832610_1659225832610.JPG",
            "publishedAt": "2022-07-31T00:09:34Z",
            "content": "Congress MP Shashi Tharoor on Saturday said the row over Adhir Ranjan Chowdhury addressing President of India Droupadi Murmu as 'rashtrapatni' by 'mistake', as Chowdhury admitted, is a non-issue. It … [+1862 chars]"
        },
        {
            "source": {
                "id": "the-times-of-india",
                "name": "The Times of India"
            },
            "author": "Reuters",
            "title": "Chinese rocket falls to Earth, Nasa says Beijing did not share information - Times of India",
            "description": "China News: A Chinese rocket fell back to Earth on Saturday over the Indian Ocean but Nasa said Beijing had not shared the \"specific trajectory information\" neede",
            "url": "https://timesofindia.indiatimes.com/world/china/chinese-rocket-falls-to-earth-nasa-says-beijing-did-not-share-information/articleshow/93243155.cms",
            "urlToImage": "https://static.toiimg.com/thumb/msid-93243181,width-1070,height-580,imgsize-1644805,resizemode-75,overlay-toi_sw,pt-32,y_pad-40/photo.jpg",
            "publishedAt": "2022-07-30T23:27:00Z",
            "content": ""
        },
        {
            "source": {
                "id": "the-times-of-india",
                "name": "The Times of India"
            },
            "author": "Dwaipayan Ghosh",
            "title": "Cooped up in 18th-floor Kolkata flat, Partha Chatterjee & Arpita Mukherjee's pedigree dogs - Times of India",
            "description": "India News: A flat on the 18th floor of a premium housing complex overlooking a golf course in south Kolkata's Tollygunge is the canine version of a castle for se",
            "url": "https://timesofindia.indiatimes.com/city/kolkata/cooped-up-in-18th-floor-kolkata-flat-partha-arpitas-pedigree-dogs/articleshow/93242212.cms",
            "urlToImage": "https://static.toiimg.com/thumb/msid-93242217,width-1070,height-580,imgsize-1356588,resizemode-75,overlay-toi_sw,pt-32,y_pad-40/photo.jpg",
            "publishedAt": "2022-07-30T20:39:00Z",
            "content": ""
        },
        {
            "source": {
                "id": null,
                "name": "The Indian Express"
            },
            "author": "Aranya Shankar",
            "title": "Delhi Today, Delhi Excise Policy 2022-23 : After row involving Lt Governor, Delhi rolls back new liquor policy - The Indian Express",
            "description": "From August 1, liquor will be sold only through government outlets in the Capital.",
            "url": "https://indianexpress.com/article/cities/delhi/delhi-rolls-back-new-liquor-policy-manish-sisodia-8060485/",
            "urlToImage": "https://images.indianexpress.com/2022/07/Sisodia.jpg",
            "publishedAt": "2022-07-30T19:53:40Z",
            "content": "From August 1, liquor will be sold only through government outlets in the Capital.\r\nWe have decided to end the new policy and given directions for government shops to open I have ordered the Chief Se… [+3737 chars]"
        },
        {
            "source": {
                "id": "the-times-of-india",
                "name": "The Times of India"
            },
            "author": "Samir Jain",
            "title": "Weekly Horoscope, 31 July to 6 August 2022: Check predictions for all zodiac signs - Times of India",
            "description": "Horoscope(Old) News: Read your horoscope predictions to know what the stars have in store for you this week:",
            "url": "https://timesofindia.indiatimes.com/astrology/horoscope/weekly-horoscope-31-july-to-6-august-2022-check-predictions-for-all-zodiac-signs/articleshow/93224341.cms",
            "urlToImage": "https://static.toiimg.com/thumb/msid-93224295,width-1070,height-580,imgsize-238857,resizemode-75,overlay-toi_sw,pt-32,y_pad-40/photo.jpg",
            "publishedAt": "2022-07-30T19:31:00Z",
            "content": ""
        },
        {
            "source": {
                "id": null,
                "name": "NDTV News"
            },
            "author": null,
            "title": "US President Joe Biden Tests Positive For Covid Again - NDTV",
            "description": "US President Joe Biden tested positive for Covid-19 for a second time and is returning to isolation though he \"continues to feel quite well,\" his White House doctor said Saturday.",
            "url": "https://www.ndtv.com/world-news/us-president-joe-biden-tests-positive-for-covid-again-report-3209815",
            "urlToImage": "https://c.ndtvimg.com/2022-07/n24017gg_joe-biden-afp_625x300_14_July_22.jpg",
            "publishedAt": "2022-07-30T19:12:33Z",
            "content": "\"This in fact represents 'rebound' positivity,\" the Presidential physician said. (File)\r\nWashington: Joe Biden has tested positive for Covid-19 for a second time and is returning to isolation, his Wh… [+1241 chars]"
        },
        {
            "source": {
                "id": "google-news",
                "name": "Google News"
            },
            "author": null,
            "title": "Winging it across the English Channel - The Hindu",
            "description": null,
            "url": "https://news.google.com/__i/rss/rd/articles/CBMiW2h0dHBzOi8vd3d3LnRoZWhpbmR1LmNvbS9jaGlsZHJlbi93aW5naW5nLWl0LWFjcm9zcy10aGUtZW5nbGlzaC1jaGFubmVsL2FydGljbGU2NTY2NTkwNC5lY2XSAWBodHRwczovL3d3dy50aGVoaW5kdS5jb20vY2hpbGRyZW4vd2luZ2luZy1pdC1hY3Jvc3MtdGhlLWVuZ2xpc2gtY2hhbm5lbC9hcnRpY2xlNjU2NjU5MDQuZWNlL2FtcC8?oc=5",
            "urlToImage": null,
            "publishedAt": "2022-07-30T18:46:00Z",
            "content": null
        },
        {
            "source": {
                "id": null,
                "name": "Northeast Now"
            },
            "author": "NE NOW NEWS",
            "title": "Wordle Today, July 31 2022: Get The Answer, Hints #407 - Northeast Now",
            "description": "Wordle is an exciting and the most popular word-guessing game, and its new word of the day for today, July 31, 2022 is out.",
            "url": "http://nenow.in/wordle/wordle-today-july-31-2022-get-the-answer-hints-407.html",
            "urlToImage": "https://nenow.in/wp-content/uploads/2022/07/wordle-answer-today-2022.webp",
            "publishedAt": "2022-07-30T18:06:59Z",
            "content": "Wordle is an exciting and the most popular word-guessing game, and its new word of the day for today, July 31, 2022 is out.\r\nThe New York Times-owned game ignites players minds to guess a five-letter… [+1282 chars]"
        },
        {
            "source": {
                "id": null,
                "name": "NDTV News"
            },
            "author": null,
            "title": "\"Compelled By...\": Shiv Sena Leader Arjun Khotkar Joins Eknath Shinde Camp - NDTV",
            "description": "Shiv Sena leader and former Maharashtra minister Arjun Khotkar on Saturday said he has joined Chief Minister Eknath Shinde's faction due to certain \"circumstances and problems.\"",
            "url": "https://www.ndtv.com/india-news/arjun-khotkar-compelled-by-shiv-sena-leader-arjun-khotkar-joins-eknath-shinde-camp-3208847",
            "urlToImage": "https://c.ndtvimg.com/2022-07/leiiphhs_arjun-khotkar_625x300_30_July_22.jpg",
            "publishedAt": "2022-07-30T17:42:26Z",
            "content": "Arjun Khotkar was recently promoted as a Shiv Sena deputy leader.\r\nJalna, Maharashtra: Shiv Sena leader and former Maharashtra minister Arjun Khotkar on Saturday said he has joined Chief Minister Ekn… [+1397 chars]"
        },
        {
            "source": {
                "id": null,
                "name": "Hindustan Times"
            },
            "author": "HT Tech",
            "title": "Secret of distant dwarf galaxy formation revealed courtesy ISRO AstroSat; triumph for Indian research - HT Tech",
            "description": "Indian researchers have just made a startling revelation about distant dwarf galaxy formation. Know what the study says.",
            "url": "https://tech.hindustantimes.com/tech/news/secret-of-distant-dwarf-galaxy-formation-revealed-courtesy-isro-astrosat-triumph-for-indian-research-71659202562704.html",
            "urlToImage": "https://images.hindustantimes.com/tech/img/2022/07/30/1600x900/image001SPE4_1659202630870_1659202682893_1659202682893.jpg",
            "publishedAt": "2022-07-30T17:38:35Z",
            "content": "Scientists have been exploring for a long time how galaxies, the basic building blocks of our Universe, emerged and evolved into the current ones. Now, a study by Tezpur University researchers along … [+1854 chars]"
        },
        {
            "source": {
                "id": null,
                "name": "Hindustan Times"
            },
            "author": "HT Sports Desk",
            "title": "Rohit, Kohli rested, Shikhar Dhawan to lead India in Zimbabwe ODIs - Hindustan Times",
            "description": "India squad for Zimbabwe ODIs: Shikhar Dhawan was named as captain while all-rounders Deepak Chahar and Washington Sundar returned from injury breaks.",
            "url": "https://www.hindustantimes.com/cricket/rohit-kohli-rested-shikhar-dhawan-to-lead-india-in-zimbabwe-odis-101659192708594.html",
            "urlToImage": "https://images.hindustantimes.com/img/2022/07/30/1600x900/West-Indies-India-Cricket-12_1659192821900_1659192821900_1659192841368_1659192841368.jpg",
            "publishedAt": "2022-07-30T16:21:05Z",
            "content": "Rohit Sharma, Virat Kohli, Rishabh Pant, Jasprit Bumrah, Hardik Pandya, Bhuvneshwar Kumar, Yuzvendra Chahal, Ravindra Jadeja, were all rested as India announced a similar-looking squad for the three-… [+1670 chars]"
        },
        {
            "source": {
                "id": null,
                "name": "Business Standard"
            },
            "author": "Raghav Aggarwal",
            "title": "Clear your power dues, PM Modi reminds states; here is what they owe - Business Standard",
            "description": "States and UTs in total owe over Rs 1 trillion to gencos and about Rs 13 trillion to discoms with Maharashtra owing the maximum",
            "url": "https://www.business-standard.com/article/economy-policy/clear-your-power-dues-pm-modi-reminds-states-here-is-what-they-owe-122073001086_1.html",
            "urlToImage": "https://bsmedia.business-standard.com/_media/bs/img/article/2017-09/12/full/1505235334-4919.jpg",
            "publishedAt": "2022-07-30T16:17:00Z",
            "content": "Prime Minister Narendra Modi on Saturday urged state governments to pay the money they owe to power distribution companies (discoms) and generating companies (gencos). He added that the outstanding d… [+3358 chars]"
        },
        {
            "source": {
                "id": null,
                "name": "Moneycontrol"
            },
            "author": "PTI",
            "title": "5G spectrum sale nears Rs 1.50 lakh crore mark on Day 5; bidding to resume on July 31 - Moneycontrol",
            "description": "The total value of bids in the telecom spectrum auction, which began on July 26, has come within striking distance of the Rs 1.50 lakh crore mark.",
            "url": "https://www.moneycontrol.com/news/business/5g-spectrum-sale-nears-rs-1-50-lakh-crore-mark-on-day-5-bidding-to-resume-on-july-31-8922411.html",
            "urlToImage": "https://images.moneycontrol.com/static-mcnews/2022/06/6-5G-evolution-around-the-world-770x433.jpg",
            "publishedAt": "2022-07-30T16:15:12Z",
            "content": "The auction of the 5G spectrum capable of offering ultra-high-speed internet garnered bids worth about Rs 1,49,966 crore on the fifth day of sale on July 30 and the bidding is expected to continue on… [+3000 chars]"
        }
    ]
}